jupyter_ovh/__init__.py
jupyter_ovh/_version.py
jupyter_ovh/handlers.py
jupyter_ovh/tests/__init__.py
jupyter_ovh/tests/test_handlers.py
jupyter_ovh-0.0.2.data/data/etc/jupyter/jupyter_notebook_config.d/jupyter_ovh.json
jupyter_ovh-0.0.2.data/data/etc/jupyter/jupyter_server_config.d/jupyter_ovh.json
jupyter_ovh-0.0.2.data/data/share/jupyter/labextensions/@datalayer/jupyter-ovh/build_log.json
jupyter_ovh-0.0.2.data/data/share/jupyter/labextensions/@datalayer/jupyter-ovh/package.json
jupyter_ovh-0.0.2.data/data/share/jupyter/labextensions/@datalayer/jupyter-ovh/schemas/@datalayer/jupyter-admin/package.json.orig
jupyter_ovh-0.0.2.data/data/share/jupyter/labextensions/@datalayer/jupyter-ovh/schemas/@datalayer/jupyter-admin/plugin.json
jupyter_ovh-0.0.2.data/data/share/jupyter/labextensions/@datalayer/jupyter-ovh/static/lib_index_js.4348b810ae8dc12e002f.js
jupyter_ovh-0.0.2.data/data/share/jupyter/labextensions/@datalayer/jupyter-ovh/static/lib_index_js.4348b810ae8dc12e002f.js.map
jupyter_ovh-0.0.2.data/data/share/jupyter/labextensions/@datalayer/jupyter-ovh/static/remoteEntry.60045aa25abfdbe55e4f.js
jupyter_ovh-0.0.2.data/data/share/jupyter/labextensions/@datalayer/jupyter-ovh/static/remoteEntry.60045aa25abfdbe55e4f.js.map
jupyter_ovh-0.0.2.data/data/share/jupyter/labextensions/@datalayer/jupyter-ovh/static/style.js
jupyter_ovh-0.0.2.data/data/share/jupyter/labextensions/@datalayer/jupyter-ovh/static/style_index_js.09ea6e1de3ce833faf40.js
jupyter_ovh-0.0.2.data/data/share/jupyter/labextensions/@datalayer/jupyter-ovh/static/style_index_js.09ea6e1de3ce833faf40.js.map
jupyter_ovh-0.0.2.data/data/share/jupyter/labextensions/@datalayer/jupyter-ovh/static/vendors-node_modules_css-loader_dist_runtime_api_js-node_modules_css-loader_dist_runtime_cssW-72eba1.bac0ab4f283009af8f3d.js
jupyter_ovh-0.0.2.dist-info/METADATA
jupyter_ovh-0.0.2.dist-info/WHEEL
jupyter_ovh-0.0.2.dist-info/licenses/LICENSE
jupyter_ovh-0.0.2.dist-info/RECORD
